hcle_py/__init__.py
hcle_py/_hcle_py.cp313-win_amd64.pyd
hcle_py/data/arkanoid.bin
hcle_py/data/baseball.bin
hcle_py/data/bubblebobble.bin
hcle_py/data/drmario.bin
hcle_py/data/excitebike.bin
hcle_py/data/golf.bin
hcle_py/data/kungfu.bin
hcle_py/data/lolo1.bin
hcle_py/data/mariobros.bin
hcle_py/data/mtpo.bin
hcle_py/data/smb1.bin
hcle_py/data/smb1_rectangle.bin
hcle_py/data/smb2.bin
hcle_py/data/smb3.bin
hcle_py/data/tetris.bin
hcle_py/data/tmnt.bin
hcle_py/data/zelda1.bin
hcle_py/env.py
hcle_py/opencv_core4.dll
hcle_py/opencv_imgproc4.dll
hcle_py/python313.dll
hcle_py/registration.py
hcle_py/SDL2.dll
hcle_py/vector_env.py
hcle_py/zlib1.dll
hcle_py-0.1.11.dist-info/METADATA
hcle_py-0.1.11.dist-info/WHEEL
hcle_py-0.1.11.dist-info/licenses/LICENCE
hcle_py-0.1.11.dist-info/RECORD
