Metadata-Version: 2.2
Name: hcle_py
Version: 0.1.11
Summary: A High-performance C++ Learning Environment
Author-Email: Hal Kolb <hal@kolb.com>
Requires-Python: >=3.10
Requires-Dist: numpy
Requires-Dist: gymnasium
